{"attributes": {"visState": "{\"title\":\"Top Error Messages v2\",\"type\":\"table\",\"params\":{\"perPage\":10,\"showPartialRows\":false,\"showMeticsAtAllLevels\":false,\"sort\":{\"columnIndex\":null,\"direction\":null},\"showTotal\":false,\"totalFunc\":\"sum\"},\"aggs\":[{\"id\":\"1\",\"enabled\":true,\"type\":\"count\",\"schema\":\"metric\",\"params\":{}},{\"id\":\"2\",\"enabled\":true,\"type\":\"terms\",\"schema\":\"bucket\",\"params\":{\"field\":\"history.actor.keyword\",\"size\":5,\"order\":\"desc\",\"orderBy\":\"1\",\"customLabel\":\"Actor\"}},{\"id\":\"3\",\"enabled\":true,\"type\":\"terms\",\"schema\":\"bucket\",\"params\":{\"field\":\"history.message.keyword\",\"size\":5,\"order\":\"desc\",\"orderBy\":\"1\",\"customLabel\":\"Message\"}},{\"id\":\"4\",\"enabled\":true,\"type\":\"terms\",\"schema\":\"bucket\",\"params\":{\"field\":\"history.operation.keyword\",\"size\":5,\"order\":\"desc\",\"orderBy\":\"1\",\"customLabel\":\"Operation\"}}]}", "description": "", "title": "Top Error Messages v2", "uiStateJSON": "{\"vis\":{\"params\":{\"sort\":{\"columnIndex\":null,\"direction\":null}}}}", "version": 1, "kibanaSavedObjectMeta": {"searchSourceJSON": "{\"index\":\"04e06060-50bf-11e9-b3a3-7302725859d5\",\"filter\":[],\"query\":{\"query\":\"\",\"language\":\"lucene\"}}"}}, "version": 3, "type": "visualization", "id": "a9d9d120-38f8-11e9-beac-8d2beda26615", "updated_at": "2019-03-27T18:37:46.426Z"}