{"attributes": {"visState": "{\"title\":\"Closed loop failed action : needs attention\",\"type\":\"table\",\"params\":{\"perPage\":5,\"showMeticsAtAllLevels\":false,\"showPartialRows\":false,\"showTotal\":false,\"sort\":{\"columnIndex\":null,\"direction\":null},\"totalFunc\":\"sum\",\"type\":\"table\"},\"aggs\":[{\"id\":\"1\",\"enabled\":true,\"type\":\"count\",\"schema\":\"metric\",\"params\":{}},{\"id\":\"2\",\"enabled\":true,\"type\":\"terms\",\"schema\":\"bucket\",\"params\":{\"field\":\"closedLoopControlName.keyword\",\"size\":5,\"order\":\"desc\",\"orderBy\":\"1\"}}],\"listeners\":{}}", "description": "", "title": "Closed loop failed action : needs attention", "uiStateJSON": "{\"vis\":{\"params\":{\"sort\":{\"columnIndex\":null,\"direction\":null}}}}", "version": 1, "savedSearchId": "AWIlAjTaDjJ4k3sPXRe1", "kibanaSavedObjectMeta": {"searchSourceJSON": "{}"}}, "version": 1, "type": "visualization", "id": "AWIlBLT7DjJ4k3sPXRe7", "updated_at": "2018-09-28T09:13:44.755Z"}